{
  "users": [
    {
      "id": "1",
      "username": "student",
      "password": "123456",
      "name": "校园用户",
      "college": "计算机学院",
      "grade": "2023级",
      "avatar": "",
      "bio": "热爱校园生活，喜欢分享闲置好物。"
    },
    {
      "username": "nihao",
      "password": "123456",
      "name": "宋",
      "college": "计算机学院",
      "grade": "2024级",
      "avatar": "",
      "bio": "这个同学还没有填写个人简介。",
      "id": "GcmbSQ2sMLg"
    }
  ],
  "trades": [
    {
      "id": "1",
      "title": "出闲置教材《软件工程导论》，九成新，可小刀",
      "category": "教材",
      "price": 35,
      "originalPrice": 59,
      "condition": "九成新",
      "images": [
        "https://images.unsplash.com/photo-1532012197267-da84d127e765?w=400&h=300&fit=crop"
      ],
      "description": "软件工程导论（第6版），只有前面几章有划线笔记，整体很新。期末考完了低价出。",
      "location": "主校区",
      "contact": "138****1234",
      "publisherId": 1,
      "publisherName": "张明",
      "publisherAvatar": "https://api.dicebear.com/7.x/avataaars/svg?seed=zhangming",
      "createdAt": "2026-06-28T10:00:00",
      "status": "active"
    },
    {
      "id": "2",
      "title": "苹果 AirPods 二代，使用半年，功能完好",
      "category": "电子产品",
      "price": 350,
      "originalPrice": 999,
      "condition": "九成新",
      "images": [
        "https://images.unsplash.com/photo-1583394838336-acd977736f90?w=400&h=300&fit=crop"
      ],
      "description": "AirPods二代有线充电版，耳机和充电盒功能正常，续航没问题，送一根原装线。",
      "location": "主校区",
      "contact": "138****5678",
      "publisherId": 2,
      "publisherName": "李思思",
      "publisherAvatar": "https://api.dicebear.com/7.x/avataaars/svg?seed=lisi",
      "createdAt": "2026-06-27T14:30:00",
      "status": "active"
    },
    {
      "id": "3",
      "title": "全新保温杯，抽奖中的，低价出",
      "category": "生活用品",
      "price": 20,
      "originalPrice": 89,
      "condition": "全新",
      "images": [
        "https://images.unsplash.com/photo-1602143407151-7111542de6e8?w=400&h=300&fit=crop"
      ],
      "description": "抽奖中的保温杯，500ml容量，不锈钢内胆，全新未拆封，颜色随机。",
      "location": "东校区",
      "contact": "139****2345",
      "publisherId": 3,
      "publisherName": "王强",
      "publisherAvatar": "https://api.dicebear.com/7.x/avataaars/svg?seed=wangqiang",
      "createdAt": "2026-06-26T09:15:00",
      "status": "active"
    },
    {
      "id": "4",
      "title": "小米手环7，戴了两个月，很新",
      "category": "电子产品",
      "price": 120,
      "originalPrice": 249,
      "condition": "九成新",
      "images": [
        "https://images.unsplash.com/photo-1575311373937-040b8e1fd5b6?w=400&h=300&fit=crop"
      ],
      "description": "小米手环7标准版，黑色，带原装充电器。屏幕无划痕，功能全正常。",
      "location": "西校区",
      "contact": "139****3456",
      "publisherId": 4,
      "publisherName": "赵敏",
      "publisherAvatar": "https://api.dicebear.com/7.x/avataaars/svg?seed=zhaomin",
      "createdAt": "2026-06-25T16:45:00",
      "status": "active"
    },
    {
      "id": "5",
      "title": "考研英语词汇书，已上岸，转给有缘人",
      "category": "教材",
      "price": 15,
      "originalPrice": 49,
      "condition": "七成新",
      "images": [
        "https://images.unsplash.com/photo-1495446815901-a7297e633e8d?w=400&h=300&fit=crop"
      ],
      "description": "考研英语词汇书（恋练有词），前面部分有笔记，后面基本全新。附送英语真题一份。",
      "location": "主校区",
      "contact": "137****4567",
      "publisherId": 5,
      "publisherName": "陈晨",
      "publisherAvatar": "https://api.dicebear.com/7.x/avataaars/svg?seed=chenchen",
      "createdAt": "2026-06-24T11:20:00",
      "status": "active"
    },
    {
      "id": "6",
      "title": "吉他九成新，带教程书和调音器",
      "category": "其他",
      "price": 150,
      "originalPrice": 399,
      "condition": "九成新",
      "images": [
        "https://images.unsplash.com/photo-1510915361894-db8b60106cb1?w=400&h=300&fit=crop"
      ],
      "description": "41寸民谣吉他，原木色，买来没弹几次，送一本吉他入门教程和调音器。",
      "location": "南校区",
      "contact": "136****5678",
      "publisherId": 1,
      "publisherName": "张明",
      "publisherAvatar": "https://api.dicebear.com/7.x/avataaars/svg?seed=zhangming",
      "createdAt": "2026-06-23T08:00:00",
      "status": "active"
    },
    {
      "id": "7",
      "title": "全新运动篮球，买大了，转手",
      "category": "体育用品",
      "price": 60,
      "originalPrice": 129,
      "condition": "全新",
      "images": [
        "https://images.unsplash.com/photo-1519861531473-9200262188bf?w=400&h=300&fit=crop"
      ],
      "description": "斯伯丁7号篮球，买成7号了，我打6号，全新未使用，带原装网兜。",
      "location": "主校区",
      "contact": "135****6789",
      "publisherId": 2,
      "publisherName": "李思思",
      "publisherAvatar": "https://api.dicebear.com/7.x/avataaars/svg?seed=lisi",
      "createdAt": "2026-06-22T19:30:00",
      "status": "active"
    },
    {
      "id": "8",
      "title": "二手显示器，预算300元以内",
      "category": "电子产品",
      "price": 280,
      "originalPrice": 699,
      "condition": "七成新",
      "images": [
        "https://images.unsplash.com/photo-1527443224154-c4a3942d3acf?w=400&h=300&fit=crop"
      ],
      "description": "戴尔24寸显示器，1080P，有HDMI和VGA接口。屏幕完好无坏点，支架有轻微使用痕迹。",
      "location": "东校区",
      "contact": "134****7890",
      "publisherId": 3,
      "publisherName": "王强",
      "publisherAvatar": "https://api.dicebear.com/7.x/avataaars/svg?seed=wangqiang",
      "createdAt": "2026-06-21T13:10:00",
      "status": "active"
    },
    {
      "id": "9",
      "title": "出售高数第六版教材，几乎全新",
      "category": "教材",
      "price": 25,
      "originalPrice": 48,
      "condition": "九成新",
      "images": [
        "https://images.unsplash.com/photo-1532012197267-da84d127e765?w=400&h=300&fit=crop"
      ],
      "description": "高等数学（同济第七版）上下册，只用过一学期，几乎全新，附送课后习题答案。",
      "location": "北校区",
      "contact": "133****8901",
      "publisherId": 4,
      "publisherName": "赵敏",
      "publisherAvatar": "https://api.dicebear.com/7.x/avataaars/svg?seed=zhaomin",
      "createdAt": "2026-06-20T10:00:00",
      "status": "active"
    },
    {
      "id": "10",
      "title": "女生冬季羽绒服，只穿过两次",
      "category": "服饰",
      "price": 80,
      "originalPrice": 359,
      "condition": "九成新",
      "images": [
        "https://images.unsplash.com/photo-1551028719-00167b16eac5?w=400&h=300&fit=crop"
      ],
      "description": "中长款黑色羽绒服，M码，含绒量90%，保暖效果好。只穿过两次，洗过一次。",
      "location": "主校区",
      "contact": "132****9012",
      "publisherId": 5,
      "publisherName": "陈晨",
      "publisherAvatar": "https://api.dicebear.com/7.x/avataaars/svg?seed=chenchen",
      "createdAt": "2026-06-19T15:00:00",
      "status": "active"
    },
    {
      "id": "11",
      "title": "富士拍立得相机 mini 7+",
      "category": "电子产品",
      "price": 200,
      "originalPrice": 399,
      "condition": "七成新",
      "images": [
        "https://images.unsplash.com/photo-1526170375885-4d8ecf77b99f?w=400&h=300&fit=crop"
      ],
      "description": "富士拍立得mini7+，白色，送一盒相纸（10张）。拍照效果很好，适合记录校园生活。",
      "location": "西校区",
      "contact": "131****0123",
      "publisherId": 1,
      "publisherName": "张明",
      "publisherAvatar": "https://api.dicebear.com/7.x/avataaars/svg?seed=zhangming",
      "createdAt": "2026-06-18T12:00:00",
      "status": "active"
    },
    {
      "id": "12",
      "title": "全新台灯，LED护眼，未拆封",
      "category": "生活用品",
      "price": 30,
      "originalPrice": 79,
      "condition": "全新",
      "images": [
        "https://images.unsplash.com/photo-1507003211169-0a1dd7228f2d?w=400&h=300&fit=crop"
      ],
      "description": "LED护眼台灯，三档亮度调节，USB充电，全新未拆封。",
      "location": "主校区",
      "contact": "130****1234",
      "publisherId": 2,
      "publisherName": "李思思",
      "publisherAvatar": "https://api.dicebear.com/7.x/avataaars/svg?seed=lisi",
      "createdAt": "2026-06-17T09:30:00",
      "status": "active"
    }
  ],
  "lostFounds": [
    {
      "id": "1",
      "type": "拾到",
      "itemName": "校园卡",
      "images": [
        "https://images.unsplash.com/photo-1591696205602-2f950c417cb9?w=400&h=300&fit=crop"
      ],
      "description": "在东区图书馆二楼自习区拾到校园卡一张，学号2024******，请失主联系认领。",
      "location": "东区图书馆",
      "happenedAt": "2026-06-28T14:00:00",
      "contact": "138****1234",
      "publisherId": 6,
      "publisherName": "刘芳",
      "publisherAvatar": "https://api.dicebear.com/7.x/avataaars/svg?seed=liufang",
      "createdAt": "2026-06-28T15:30:00",
      "status": "active"
    },
    {
      "id": "2",
      "type": "丢失",
      "itemName": "黑色耳机盒",
      "images": [
        "https://images.unsplash.com/photo-1583394838336-acd977736f90?w=400&h=300&fit=crop"
      ],
      "description": "西门打印店附近丢失黑色AirPods耳机盒，里面有一只耳机。有捡到的好心人请联系我，万分感谢！",
      "location": "西门打印店",
      "happenedAt": "2026-06-27T18:00:00",
      "contact": "139****5678",
      "publisherId": 7,
      "publisherName": "周杰",
      "publisherAvatar": "https://api.dicebear.com/7.x/avataaars/svg?seed=zhoujie",
      "createdAt": "2026-06-27T19:00:00",
      "status": "active"
    },
    {
      "id": "3",
      "type": "拾到",
      "itemName": "充电宝",
      "images": [
        "https://picsum.photos/seed/powerbank/400/300"
      ],
      "description": "在主校区教学楼301教室拾到白色充电宝一个，20000mAh，请失主到教务处认领。",
      "location": "主校区教学楼",
      "happenedAt": "2026-06-27T10:00:00",
      "contact": "139****6789",
      "publisherId": 8,
      "publisherName": "吴芳",
      "publisherAvatar": "https://api.dicebear.com/7.x/avataaars/svg?seed=wufang",
      "createdAt": "2026-06-27T11:00:00",
      "status": "active"
    },
    {
      "id": "4",
      "type": "丢失",
      "itemName": "灰色双肩包",
      "images": [
        "https://images.unsplash.com/photo-1553062407-98eeb64c6a62?w=400&h=300&fit=crop"
      ],
      "description": "在操场跑道边丢失灰色双肩包一个，内含笔记本电脑和课本。电脑里有重要论文资料，急寻！",
      "location": "操场",
      "happenedAt": "2026-06-26T20:00:00",
      "contact": "137****8901",
      "publisherId": 9,
      "publisherName": "孙莉",
      "publisherAvatar": "https://api.dicebear.com/7.x/avataaars/svg?seed=sunli",
      "createdAt": "2026-06-26T21:00:00",
      "status": "active"
    },
    {
      "id": "5",
      "type": "拾到",
      "itemName": "钥匙一串",
      "images": [
        "https://picsum.photos/seed/keys/400/300"
      ],
      "description": "在操场跑道边拾到钥匙一串，共3把钥匙+一个红色门禁卡挂件。请失主到游泳馆前台领取。",
      "location": "操场",
      "happenedAt": "2026-06-26T17:00:00",
      "contact": "136****9012",
      "publisherId": 10,
      "publisherName": "郑伟",
      "publisherAvatar": "https://api.dicebear.com/7.x/avataaars/svg?seed=zhengwei",
      "createdAt": "2026-06-26T18:00:00",
      "status": "active"
    },
    {
      "id": "6",
      "type": "丢失",
      "itemName": "学生证",
      "images": [
        "https://images.unsplash.com/photo-1586282391129-76a6df230234?w=400&h=300&fit=crop"
      ],
      "description": "在三食堂吃饭时丢失学生证，计算机学院2023级，学号2023******。补办很麻烦，希望好心人捡到联系我。",
      "location": "三食堂",
      "happenedAt": "2026-06-25T12:00:00",
      "contact": "135****0123",
      "publisherId": 11,
      "publisherName": "钱程",
      "publisherAvatar": "https://api.dicebear.com/7.x/avataaars/svg?seed=qiancheng",
      "createdAt": "2026-06-25T13:00:00",
      "status": "active"
    },
    {
      "id": "7",
      "type": "拾到",
      "itemName": "雨伞",
      "images": [
        "https://images.unsplash.com/photo-1507003211169-0a1dd7228f2d?w=400&h=300&fit=crop"
      ],
      "description": "三食堂拾到蓝色折叠雨伞一把，放在进门右手边失物招领处，请失主尽快认领。",
      "location": "三食堂",
      "happenedAt": "2026-06-25T11:30:00",
      "contact": "134****1234",
      "publisherId": 12,
      "publisherName": "冯明",
      "publisherAvatar": "https://api.dicebear.com/7.x/avataaars/svg?seed=fengming",
      "createdAt": "2026-06-25T12:00:00",
      "status": "active"
    },
    {
      "id": "8",
      "type": "丢失",
      "itemName": "手表",
      "images": [
        "https://images.unsplash.com/photo-1524592094714-0f0654e20314?w=400&h=300&fit=crop"
      ],
      "description": "在体育馆更衣室丢失卡西欧电子手表一块，黑色表盘。是生日礼物，对我很重要，恳请拾到者联系！",
      "location": "体育馆",
      "happenedAt": "2026-06-24T16:00:00",
      "contact": "133****5678",
      "publisherId": 13,
      "publisherName": "蒋文",
      "publisherAvatar": "https://api.dicebear.com/7.x/avataaars/svg?seed=jiangwen",
      "createdAt": "2026-06-24T17:00:00",
      "status": "active"
    },
    {
      "id": "9",
      "type": "拾到",
      "itemName": "钱包",
      "images": [
        "https://images.unsplash.com/photo-1591696205602-2f950c417cb9?w=400&h=300&fit=crop"
      ],
      "description": "在主校道旁边的长椅上拾到黑色短款钱包一个，内含少量现金和银行卡。请失主到保卫处认领。",
      "location": "主校道",
      "happenedAt": "2026-06-23T15:00:00",
      "contact": "132****9012",
      "publisherId": 14,
      "publisherName": "何琳",
      "publisherAvatar": "https://api.dicebear.com/7.x/avataaars/svg?seed=helin",
      "createdAt": "2026-06-23T16:00:00",
      "status": "active"
    },
    {
      "id": "10",
      "type": "丢失",
      "itemName": "保温杯",
      "images": [
        "https://images.unsplash.com/photo-1602143407151-7111542de6e8?w=400&h=300&fit=crop"
      ],
      "description": "在图书馆五楼自习区丢失白色保温杯，杯身有\"加油\"贴纸。用习惯了不想换，希望拾到的同学联系我。",
      "location": "图书馆",
      "happenedAt": "2026-06-22T21:00:00",
      "contact": "131****3456",
      "publisherId": 15,
      "publisherName": "马超",
      "publisherAvatar": "https://api.dicebear.com/7.x/avataaars/svg?seed=machao",
      "createdAt": "2026-06-22T22:00:00",
      "status": "active"
    }
  ],
  "groupBuys": [
    {
      "id": "1",
      "title": "东区食堂三楼拼奶茶，还差2人",
      "type": "餐饮",
      "currentCount": 1,
      "targetCount": 3,
      "deadline": "2026-06-29T18:00:00",
      "meetLocation": "东区食堂三楼",
      "description": "一点点奶茶买三送一活动，拼单每人省5块！口味自选，下午六点前下单。",
      "images": [
        "https://images.unsplash.com/photo-1558857563-b371033873b8?w=400&h=300&fit=crop"
      ],
      "publisherId": 6,
      "publisherName": "刘芳",
      "publisherAvatar": "https://api.dicebear.com/7.x/avataaars/svg?seed=liufang",
      "createdAt": "2026-06-28T11:00:00",
      "status": "active"
    },
    {
      "id": "2",
      "title": "周五晚上拼车去高铁站，还差2人",
      "type": "出行",
      "currentCount": 2,
      "targetCount": 4,
      "deadline": "2026-07-03T12:00:00",
      "meetLocation": "北门",
      "description": "周五晚上7点从学校北门拼车去高铁站，滴滴打车，人均10元左右。",
      "images": [
        "https://images.unsplash.com/photo-1449965408869-eaa3f722e40d?w=400&h=300&fit=crop"
      ],
      "publisherId": 7,
      "publisherName": "周杰",
      "publisherAvatar": "https://api.dicebear.com/7.x/avataaars/svg?seed=zhoujie",
      "createdAt": "2026-06-27T09:00:00",
      "status": "active"
    },
    {
      "id": "3",
      "title": "拼单买水果，一箱车厘子平均分",
      "type": "购物",
      "currentCount": 2,
      "targetCount": 5,
      "deadline": "2026-06-30T20:00:00",
      "meetLocation": "南门水果店",
      "description": "京东生鲜团购，5斤装车厘子JJ级，一箱148元。5人拼单每人不到30块！",
      "images": [
        "https://images.unsplash.com/photo-1559181567-c3190ca9959b?w=400&h=300&fit=crop"
      ],
      "publisherId": 8,
      "publisherName": "吴芳",
      "publisherAvatar": "https://api.dicebear.com/7.x/avataaars/svg?seed=wufang",
      "createdAt": "2026-06-26T14:00:00",
      "status": "active"
    },
    {
      "id": "4",
      "title": "英语四级网课拼团，还剩3个名额",
      "type": "其他",
      "currentCount": 2,
      "targetCount": 5,
      "deadline": "2026-07-01T00:00:00",
      "meetLocation": "线上",
      "description": "考虫英语四级系统班，原价199，五人拼团每人仅需89元。有意向的同学一起拼！",
      "images": [
        "https://images.unsplash.com/photo-1434030216411-0b793f4b4173?w=400&h=300&fit=crop"
      ],
      "publisherId": 9,
      "publisherName": "孙莉",
      "publisherAvatar": "https://api.dicebear.com/7.x/avataaars/svg?seed=sunli",
      "createdAt": "2026-06-25T16:00:00",
      "status": "active"
    },
    {
      "id": "5",
      "title": "周末一起去宜家拼单购物",
      "type": "购物",
      "currentCount": 1,
      "targetCount": 4,
      "deadline": "2026-07-04T10:00:00",
      "meetLocation": "西门",
      "description": "周末去宜家买宿舍收纳用品，拼车一起去，一起拼单还能享受会员折扣。",
      "images": [
        "https://images.unsplash.com/photo-1555041469-a586c61ea9bc?w=400&h=300&fit=crop"
      ],
      "publisherId": 10,
      "publisherName": "郑伟",
      "publisherAvatar": "https://api.dicebear.com/7.x/avataaars/svg?seed=zhengwei",
      "createdAt": "2026-06-24T11:00:00",
      "status": "active"
    },
    {
      "id": "6",
      "title": "拼单买篮球，三人平分",
      "type": "购物",
      "currentCount": 1,
      "targetCount": 3,
      "deadline": "2026-06-30T18:00:00",
      "meetLocation": "体育馆",
      "description": "斯伯丁7号篮球，原价299，三人拼单每人100块。平时一起打球的兄弟来拼！",
      "images": [
        "https://images.unsplash.com/photo-1519861531473-9200262188bf?w=400&h=300&fit=crop"
      ],
      "publisherId": 11,
      "publisherName": "钱程",
      "publisherAvatar": "https://api.dicebear.com/7.x/avataaars/svg?seed=qiancheng",
      "createdAt": "2026-06-23T20:00:00",
      "status": "active"
    },
    {
      "id": "7",
      "title": "一起点外卖，凑起送价",
      "type": "餐饮",
      "currentCount": 1,
      "targetCount": 3,
      "deadline": "2026-06-29T12:00:00",
      "meetLocation": "12栋宿舍楼下",
      "description": "想点华莱士，起送价50还差30。有在12栋的同学一起拼单吗？中午送到。",
      "images": [
        "https://images.unsplash.com/photo-1568901346375-23c9450c58cd?w=400&h=300&fit=crop"
      ],
      "publisherId": 12,
      "publisherName": "冯明",
      "publisherAvatar": "https://api.dicebear.com/7.x/avataaars/svg?seed=fengming",
      "createdAt": "2026-06-23T11:00:00",
      "status": "active"
    },
    {
      "id": "8",
      "title": "网易云音乐会员拼车",
      "type": "其他",
      "currentCount": 2,
      "targetCount": 6,
      "deadline": "2026-07-05T00:00:00",
      "meetLocation": "线上",
      "description": "网易云音乐黑胶VIP年卡拼车，6人家庭共享，每人仅需25元/年。最后4个名额！",
      "images": [
        "https://images.unsplash.com/photo-1514525253161-7a46d19cd819?w=400&h=300&fit=crop"
      ],
      "publisherId": 13,
      "publisherName": "蒋文",
      "publisherAvatar": "https://api.dicebear.com/7.x/avataaars/svg?seed=jiangwen",
      "createdAt": "2026-06-22T15:00:00",
      "status": "active"
    },
    {
      "id": "9",
      "title": "游泳馆办卡拼团",
      "type": "其他",
      "currentCount": 3,
      "targetCount": 5,
      "deadline": "2026-07-02T18:00:00",
      "meetLocation": "游泳馆",
      "description": "学校游泳馆半年卡原价300，5人团购价每人180。已经有3人了，还差2个！",
      "images": [
        "https://images.unsplash.com/photo-1560090995-01632a28895b?w=400&h=300&fit=crop"
      ],
      "publisherId": 14,
      "publisherName": "何琳",
      "publisherAvatar": "https://api.dicebear.com/7.x/avataaars/svg?seed=helin",
      "createdAt": "2026-06-21T09:00:00",
      "status": "active"
    },
    {
      "id": "10",
      "title": "拼单买咖啡豆，手冲爱好者来",
      "type": "购物",
      "currentCount": 1,
      "targetCount": 4,
      "deadline": "2026-07-03T12:00:00",
      "meetLocation": "西门外咖啡店",
      "description": "从淘宝买精品咖啡豆，四人拼单免运费。耶加雪菲水洗，454g装，拼单价45元。",
      "images": [
        "https://images.unsplash.com/photo-1495474472287-4d71bcdd2085?w=400&h=300&fit=crop"
      ],
      "publisherId": 15,
      "publisherName": "马超",
      "publisherAvatar": "https://api.dicebear.com/7.x/avataaars/svg?seed=machao",
      "createdAt": "2026-06-20T14:00:00",
      "status": "active"
    }
  ],
  "errands": [
    {
      "id": "1",
      "title": "求帮取快递到6栋宿舍，酬谢5元",
      "type": "取快递",
      "content": "菜鸟驿站有个中通快递，不大，帮我取一下送到6栋宿舍楼下。快递码我私发你。",
      "reward": 5,
      "images": [
        "https://images.unsplash.com/photo-1580674285054-bed31e145f59?w=400&h=300&fit=crop"
      ],
      "deliveryLocation": "6栋宿舍楼下",
      "expectedTime": "今天下午6点前",
      "contact": "138****1234",
      "publisherId": 6,
      "publisherName": "刘芳",
      "publisherAvatar": "https://api.dicebear.com/7.x/avataaars/svg?seed=liufang",
      "createdAt": "2026-06-28T09:00:00",
      "status": "待接单"
    },
    {
      "id": "2",
      "title": "代购一份烧鸭饭送到图书馆，酬劳8元",
      "type": "代购",
      "content": "麻烦到二食堂烧鸭窗口买一份烧鸭饭（加卤蛋），送到图书馆三楼自习区。钱先转你。",
      "reward": 8,
      "images": [
        "https://images.unsplash.com/photo-1563379926898-05f4575a45d8?w=400&h=300&fit=crop"
      ],
      "deliveryLocation": "图书馆三楼",
      "expectedTime": "中午12点前",
      "contact": "139****5678",
      "publisherId": 7,
      "publisherName": "周杰",
      "publisherAvatar": "https://api.dicebear.com/7.x/avataaars/svg?seed=zhoujie",
      "createdAt": "2026-06-27T10:30:00",
      "status": "待接单"
    },
    {
      "id": "3",
      "title": "帮送一沓资料到行政楼3楼",
      "type": "送东西",
      "content": "有一沓资料需要从宿舍送到行政楼302办公室，急用。帮忙跑一趟，不重。",
      "reward": 10,
      "images": [
        "https://images.unsplash.com/photo-1554224155-8d04cb21cd6c?w=400&h=300&fit=crop"
      ],
      "deliveryLocation": "行政楼302",
      "expectedTime": "今天上午11点前",
      "contact": "139****6789",
      "publisherId": 8,
      "publisherName": "吴芳",
      "publisherAvatar": "https://api.dicebear.com/7.x/avataaars/svg?seed=wufang",
      "createdAt": "2026-06-27T08:00:00",
      "status": "已接单"
    },
    {
      "id": "4",
      "title": "求代取药，校医院送到12栋",
      "type": "取快递",
      "content": "在校医院开了药，但是我现在在实验室走不开。帮我去校医院药房取药送到12栋宿舍。",
      "reward": 6,
      "images": [
        "https://images.unsplash.com/photo-1587854692152-cbe660dbde88?w=400&h=300&fit=crop"
      ],
      "deliveryLocation": "12栋宿舍",
      "expectedTime": "今天下午",
      "contact": "137****8901",
      "publisherId": 9,
      "publisherName": "孙莉",
      "publisherAvatar": "https://api.dicebear.com/7.x/avataaars/svg?seed=sunli",
      "createdAt": "2026-06-26T14:00:00",
      "status": "待接单"
    },
    {
      "id": "5",
      "title": "帮买一杯生椰拿铁送到自习室",
      "type": "代购",
      "content": "瑞幸生椰拿铁一杯，少冰不另外加糖。送到图书馆四楼自习室，谢谢！",
      "reward": 5,
      "images": [
        "https://images.unsplash.com/photo-1572442388796-11668a67e53d?w=400&h=300&fit=crop"
      ],
      "deliveryLocation": "图书馆四楼",
      "expectedTime": "今天下午3点前",
      "contact": "136****9012",
      "publisherId": 10,
      "publisherName": "郑伟",
      "publisherAvatar": "https://api.dicebear.com/7.x/avataaars/svg?seed=zhengwei",
      "createdAt": "2026-06-26T11:00:00",
      "status": "已完成"
    },
    {
      "id": "6",
      "title": "帮我给女朋友送个小礼物，惊喜！",
      "type": "送东西",
      "content": "帮我送一个小礼物盒到15栋女生宿舍楼下，交给宿管阿姨转交。礼物已包装好，送到就行！",
      "reward": 12,
      "images": [
        "https://images.unsplash.com/photo-1513885535751-8b9238bd345a?w=400&h=300&fit=crop"
      ],
      "deliveryLocation": "15栋宿舍楼下",
      "expectedTime": "今晚8点前",
      "contact": "135****0123",
      "publisherId": 11,
      "publisherName": "钱程",
      "publisherAvatar": "https://api.dicebear.com/7.x/avataaars/svg?seed=qiancheng",
      "createdAt": "2026-06-25T18:00:00",
      "status": "待接单"
    },
    {
      "id": "7",
      "title": "帮取快递到西校区7栋",
      "type": "取快递",
      "content": "西校区菜鸟驿站有2个快递，一个中通一个圆通，都不大。送到西校区7栋宿舍。",
      "reward": 6,
      "images": [
        "https://images.unsplash.com/photo-1560343090-f0409e92791a?w=400&h=300&fit=crop"
      ],
      "deliveryLocation": "西校区7栋",
      "expectedTime": "今天",
      "contact": "134****1234",
      "publisherId": 12,
      "publisherName": "冯明",
      "publisherAvatar": "https://api.dicebear.com/7.x/avataaars/svg?seed=fengming",
      "createdAt": "2026-06-25T09:00:00",
      "status": "已接单"
    },
    {
      "id": "8",
      "title": "代购早餐送到机房",
      "type": "代购",
      "content": "帮我买一份鸡蛋灌饼+一杯豆浆，送到计算机学院三楼机房。赶作业走不开，拜托了！",
      "reward": 5,
      "images": [
        "https://images.unsplash.com/photo-1550547660-d9450f859349?w=400&h=300&fit=crop"
      ],
      "deliveryLocation": "计算机学院三楼机房",
      "expectedTime": "明天早上8点半前",
      "contact": "133****5678",
      "publisherId": 13,
      "publisherName": "蒋文",
      "publisherAvatar": "https://api.dicebear.com/7.x/avataaars/svg?seed=jiangwen",
      "createdAt": "2026-06-24T22:00:00",
      "status": "待接单"
    },
    {
      "id": "9",
      "title": "帮送钥匙到体育馆",
      "type": "送东西",
      "content": "我打球把钥匙落在宿舍了，室友在宿舍。帮我跑一趟拿钥匙送到体育馆给我。",
      "reward": 8,
      "images": [
        "https://images.unsplash.com/photo-1574629810360-7efbbe195018?w=400&h=300&fit=crop"
      ],
      "deliveryLocation": "体育馆前台",
      "expectedTime": "今天下午4点前",
      "contact": "132****9012",
      "publisherId": 14,
      "publisherName": "何琳",
      "publisherAvatar": "https://api.dicebear.com/7.x/avataaars/svg?seed=helin",
      "createdAt": "2026-06-23T15:00:00",
      "status": "已完成"
    },
    {
      "id": "10",
      "title": "帮买文具送到教学楼",
      "type": "代购",
      "content": "考试发现没带2B铅笔和橡皮，帮我去超市买一下送到教学楼201考场。急！！",
      "reward": 10,
      "images": [
        "https://images.unsplash.com/photo-1452860606245-08befc0ff44b?w=400&h=300&fit=crop"
      ],
      "deliveryLocation": "教学楼201",
      "expectedTime": "半小时内",
      "contact": "131****3456",
      "publisherId": 15,
      "publisherName": "马超",
      "publisherAvatar": "https://api.dicebear.com/7.x/avataaars/svg?seed=machao",
      "createdAt": "2026-06-22T08:30:00",
      "status": "已完成"
    }
  ],
  "$schema": "./node_modules/json-server/schema.json"
}